StructuralGT/GT_Params.py
StructuralGT/GT_Params_multi.py
StructuralGT/GetWeights.py
StructuralGT/__init__.py
StructuralGT/__main__.py
StructuralGT/gui_multi_image.py
StructuralGT/gui_single_image.py
StructuralGT/multi_image_settings.py
StructuralGT/process_image.py
StructuralGT/settings.py
StructuralGT/single_image_looper.py
StructuralGT/skel_ID.py
StructuralGT_RC/GT_Params.py
StructuralGT_RC/GT_Params_multi.py
StructuralGT_RC/GetWeights.py
StructuralGT_RC/__init__.py
StructuralGT_RC/__main__.py
StructuralGT_RC/gui_multi_image.py
StructuralGT_RC/gui_single_image.py
StructuralGT_RC/multi_image_settings.py
StructuralGT_RC/process_image.py
StructuralGT_RC/settings.py
StructuralGT_RC/single_image_looper.py
StructuralGT_RC/skel_ID.py
StructuralGT-1.0.1a8.dist-info/LICENSE.txt
StructuralGT-1.0.1a8.dist-info/METADATA
StructuralGT-1.0.1a8.dist-info/WHEEL
StructuralGT-1.0.1a8.dist-info/top_level.txt
StructuralGT-1.0.1a8.dist-info/RECORD
