Metadata-Version: 2.1
Name: StructuralGT
Version: 1.0.1a8
Summary: Automated graph theory analysis of digital structural networks images
Home-page: https://github.com/drewvecchio/StructuralGT
Author: drewvecchio
Author-email: vecdrew@umich.edu
License: GNU General Public License v3
Platform: UNKNOWN
Requires-Dist: numpy
Requires-Dist: scipy
Requires-Dist: scikit-image
Requires-Dist: matplotlib
Requires-Dist: networkx
Requires-Dist: opencv-python
Requires-Dist: sknw
Requires-Dist: Pillow
Requires-Dist: pandas
